http_stream_xml/__init__.py
http_stream_xml/entrez.py
http_stream_xml/socket_stream.py
http_stream_xml/version.py
http_stream_xml/xml_stream.py
http_stream_xml/examples/http_stream_example.py
http_stream_xml/examples/socket_stream_example.py
http_stream_xml-1.3.13.dist-info/METADATA
http_stream_xml-1.3.13.dist-info/WHEEL
http_stream_xml-1.3.13.dist-info/licenses/LICENSE.txt
http_stream_xml-1.3.13.dist-info/RECORD
