Metadata-Version: 2.4
Name: http-stream-xml
Version: 1.3.13
Summary: Parse XML in HTTP response on the fly, by chunks - for example NCBI (PubMed) Entrez.
Project-URL: Homepage, https://github.com/andgineer/http-stream-xml
Project-URL: documentation, https://http-stream-xml.sorokin.engineer/
Author-email: Andrey Sorokin <andrey@sorokin.engineer>
License: Copyright (c) 2019 Andrey Sorokin <filbert@ya.ru>
License-File: LICENSE.txt
Keywords: chunked,http,stream,xml
Classifier: License :: OSI Approved :: MIT License
Classifier: Operating System :: OS Independent
Classifier: Programming Language :: Python :: 3
Requires-Python: >=3.11
Requires-Dist: requests
